contextual_privacy_guard/__init__.py
contextual_privacy_guard/analyzer.py
contextual_privacy_guard/runner.py
contextual_privacy_guard/patterns/__init__.py
contextual_privacy_guard/patterns/intent_patterns.py
contextual_privacy_guard/patterns/task_patterns.py
contextual_privacy_guard/prompts/deepseek/essential_info.txt
contextual_privacy_guard/prompts/deepseek/essential_info_static.txt
contextual_privacy_guard/prompts/deepseek/intent_detection.txt
contextual_privacy_guard/prompts/deepseek/non_essential_info.txt
contextual_privacy_guard/prompts/deepseek/non_essential_info_static.txt
contextual_privacy_guard/prompts/deepseek/reformulation.txt
contextual_privacy_guard/prompts/deepseek/sensitive_info.txt
contextual_privacy_guard/prompts/deepseek/task_detection.txt
contextual_privacy_guard/prompts/llama/essential_info.txt
contextual_privacy_guard/prompts/llama/essential_info_static.txt
contextual_privacy_guard/prompts/llama/intent_detection.txt
contextual_privacy_guard/prompts/llama/non_essential_info.txt
contextual_privacy_guard/prompts/llama/non_essential_info_static.txt
contextual_privacy_guard/prompts/llama/reformulation.txt
contextual_privacy_guard/prompts/llama/sensitive_info.txt
contextual_privacy_guard/prompts/llama/task_detection.txt
contextual_privacy_guard/prompts/mixtral/essential_info.txt
contextual_privacy_guard/prompts/mixtral/essential_info_static.txt
contextual_privacy_guard/prompts/mixtral/intent_detection.txt
contextual_privacy_guard/prompts/mixtral/non_essential_info.txt
contextual_privacy_guard/prompts/mixtral/non_essential_info_static.txt
contextual_privacy_guard/prompts/mixtral/reformulation.txt
contextual_privacy_guard/prompts/mixtral/sensitive_info.txt
contextual_privacy_guard/prompts/mixtral/task_detection.txt
contextual_privacy_guard-0.1.5.dist-info/licenses/LICENSE
contextual_privacy_guard-0.1.5.dist-info/METADATA
contextual_privacy_guard-0.1.5.dist-info/WHEEL
contextual_privacy_guard-0.1.5.dist-info/entry_points.txt
contextual_privacy_guard-0.1.5.dist-info/top_level.txt
contextual_privacy_guard-0.1.5.dist-info/RECORD
