Metadata-Version: 2.4
Name: contextual-privacy-guard
Version: 0.1.5
Summary: A toolkit for safeguarding contextual privacy in LLM prompts
Home-page: https://github.com/IBM/contextual-privacy-LLM
Author: IBM Research
Author-email: ivoline@ibm.com
Requires-Python: >=3.8
License-File: LICENSE
Requires-Dist: requests>=2.0
Dynamic: author
Dynamic: author-email
Dynamic: home-page
Dynamic: license-file
Dynamic: requires-dist
Dynamic: requires-python
Dynamic: summary
